loguricorn/__init__.py
loguricorn/gunicorn.py
loguricorn/intercept.py
loguricorn-0.1.0.dist-info/LICENSE
loguricorn-0.1.0.dist-info/WHEEL
loguricorn-0.1.0.dist-info/METADATA
loguricorn-0.1.0.dist-info/RECORD
