Metadata-Version: 2.1
Name: loguricorn
Version: 0.1.0
Summary: A small package for rerouting gunicorn logs to loguru
Home-page: https://github.com/jmgilman/loguricorn
License: MIT
Keywords: loguru,gunicorn,logging
Author: Joshua Gilman
Author-email: joshuagilman@gmail.com
Requires-Python: >=3.10,<4.0
Classifier: License :: OSI Approved :: MIT License
Classifier: Programming Language :: Python :: 3
Classifier: Programming Language :: Python :: 3.10
Requires-Dist: gunicorn (>=20.1.0,<21.0.0)
Requires-Dist: loguru (>=0.6.0,<0.7.0)
Project-URL: Repository, https://github.com/jmgilman/loguricorn
